dango/__init__.py
dango/cli.py
dango/dango.py
dango/fsm.py
dango/util.py
dango/word.py
dango-0.0.1.dist-info/LICENSE
dango-0.0.1.dist-info/METADATA
dango-0.0.1.dist-info/WHEEL
dango-0.0.1.dist-info/entry_points.txt
dango-0.0.1.dist-info/top_level.txt
dango-0.0.1.dist-info/RECORD
