Metadata-Version: 2.1
Name: dango
Version: 0.0.1
Summary: An easy to use tokenizer for Japanese text, aimed at language learners and non-linguists
Home-page: https://github.com/mkartawijaya/dango
Author: Martin Kartawijaya
Author-email: pypi@m.kartawijaya.dev
License: BSD-3-Clause
Keywords: japanese,tokenization,nlp
Platform: UNKNOWN
Classifier: Development Status :: 3 - Alpha
Classifier: Programming Language :: Python :: 3
Classifier: Operating System :: OS Independent
Classifier: License :: OSI Approved :: BSD License
Classifier: Topic :: Education
Classifier: Topic :: Text Processing :: Linguistic
Classifier: Natural Language :: Japanese
Requires-Python: >=3.6
License-File: LICENSE
Requires-Dist: pygtrie (~=2.4)
Requires-Dist: SudachiPy (~=0.5.2)
Requires-Dist: SudachiDict-core (>=20210608)
Provides-Extra: dev
Requires-Dist: build (~=0.7) ; extra == 'dev'
Requires-Dist: twine (~=3.6) ; extra == 'dev'
Requires-Dist: mypy (~=0.910) ; extra == 'dev'
Requires-Dist: flake8 (~=4.0) ; extra == 'dev'
Provides-Extra: test
Requires-Dist: pytest (~=6.2) ; extra == 'test'
Requires-Dist: coverage (~=6.1) ; extra == 'test'
